{
  "projectname": "%E7%82%B9%E9%A4%90%E5%B0%8F%E7%A8%8B%E5%BA%8F",
  "setting": {
    "compileHotReLoad": true,
    "urlCheck": false
  },
  "description": "项目私有配置文件。此文件中的内容将覆盖 project.config.json 中的相同字段。项目的改动优先同步到此文件中。详见文档：https://developers.weixin.qq.com/miniprogram/dev/devtools/projectconfig.html",
  "condition": {
    "miniprogram": {
      "list": [
        {
          "name": "",
          "pathName": "pages/list/list",
          "query": "",
          "launchMode": "default",
          "scene": null
        },
        {
          "name": "",
          "pathName": "pages/order/balance/balance",
          "query": "order_id=8",
          "launchMode": "default",
          "scene": null
        },
        {
          "name": "",
          "pathName": "pages/order/detail/detail",
          "query": "order_id=5",
          "launchMode": "default",
          "scene": null
        },
        {
          "name": "",
          "pathName": "pages/order/list/list",
          "query": "",
          "launchMode": "default",
          "scene": null
        },
        {
          "name": "",
          "pathName": "pages/records/records",
          "query": "",
          "launchMode": "default",
          "scene": null
        }
      ]
    }
  }
}